camel_snake_kebab-0.3.2.dist-info/RECORD
camel_snake_kebab-0.3.2.dist-info/WHEEL
camel_snake_kebab-0.3.2.dist-info/METADATA
camel_snake_kebab-0.3.2.dist-info/metadata.json
camel_snake_kebab-0.3.2.dist-info/DESCRIPTION.rst
camel_snake_kebab-0.3.2.dist-info/top_level.txt
camel_snake_kebab/__init___test.py
camel_snake_kebab/__init__.py
camel_snake_kebab/extras.py
camel_snake_kebab/extras_test.py
camel_snake_kebab/internals/misc.py
camel_snake_kebab/internals/string_separator.py
camel_snake_kebab/internals/decorator.py
camel_snake_kebab/internals/string_separator_test.py
camel_snake_kebab/internals/__init__.py
camel_snake_kebab/internals/string_compat.py
