Metadata-Version: 2.0
Name: camel-snake-kebab
Version: 0.3.2
Summary: A Python library for word case conversions
Home-page: https://github.com/t6/camel_snake_kebab
Author: Tobias Kortkamp
Author-email: t@tobik.me
License: Eclipse Public License v1.0
Keywords: snake_case CamelCase kebab-case
Platform: UNKNOWN
Classifier: Development Status :: 5 - Production/Stable
Classifier: Intended Audience :: Developers
Classifier: Topic :: Software Development :: Build Tools
Classifier: License :: OSI Approved
Classifier: Programming Language :: Python :: 2
Classifier: Programming Language :: Python :: 2.7
Classifier: Programming Language :: Python :: 3
Classifier: Programming Language :: Python :: 3.2
Classifier: Programming Language :: Python :: 3.4
